semiauto_regression/__init__.py
semiauto_regression/custom_transformers.py
semiauto_regression/utils.py
semiauto_regression/data/__init__.py
semiauto_regression/data/data_cleaning.py
semiauto_regression/data/data_ingestion.py
semiauto_regression/data/data_preprocessing.py
semiauto_regression/features/__init__.py
semiauto_regression/features/feature_engineering.py
semiauto_regression/logger/__init__.py
semiauto_regression/model/__init__.py
semiauto_regression/model/model_building.py
semiauto_regression/model/model_evaluation.py
semiauto_regression/model/model_optimization.py
semiauto_regression/visualization/__init__.py
semiauto_regression/visualization/projectflow_report.py
semiauto_regression-0.0.2.dist-info/licenses/LICENSE
semiauto_regression-0.0.2.dist-info/METADATA
semiauto_regression-0.0.2.dist-info/WHEEL
semiauto_regression-0.0.2.dist-info/entry_points.txt
semiauto_regression-0.0.2.dist-info/top_level.txt
semiauto_regression-0.0.2.dist-info/RECORD
